CHANGELOG.rst
LICENSE.txt
MANIFEST.in
README.rst
TODO.txt
VERSION.txt
setup.cfg
setup.py
proxylog/__init__.py
proxylog/cli.py
proxylog/engine.py
proxylog/i18n.py
proxylog/pyaml.py
proxylog/test.py
proxylog.egg-info/PKG-INFO
proxylog.egg-info/SOURCES.txt
proxylog.egg-info/dependency_links.txt
proxylog.egg-info/entry_points.txt
proxylog.egg-info/requires.txt
proxylog.egg-info/top_level.txt
proxylog.egg-info/zip-safe