Metadata-Version: 1.1
Name: proxylog
Version: 0.4
Summary: A simple, xml-prettifying, colorizing, logging, HTTP proxy.
Home-page: http://github.com/metagriffin/proxylog
Author: metagriffin
Author-email: mg.pypi@uberdev.org
License: GPLv3+
Keywords: http proxy logging xml colorize prettify
Platform: any
Classifier: Development Status :: 3 - Alpha
Classifier: Intended Audience :: Developers
Classifier: Programming Language :: Python
Classifier: Operating System :: OS Independent
Classifier: Natural Language :: English
Classifier: License :: OSI Approved :: GNU General Public License v3 or later (GPLv3+)
